cnspy_rosbag2csv/CSV2ROSbag.py
cnspy_rosbag2csv/CSVLine2ROSMsg.py
cnspy_rosbag2csv/CSVParser.py
cnspy_rosbag2csv/ROSMessageTypes.py
cnspy_rosbag2csv/ROSMsg2CSVLine.py
cnspy_rosbag2csv/ROSbag2CSV.py
cnspy_rosbag2csv/ROSbagMerge.py
cnspy_rosbag2csv/ROSbag_ReTimestamp.py
cnspy_rosbag2csv/__init__.py
test/__init__.py
test/test_CSV2ROSbag.py
test/test_CSVLine2ROSMsg.py
test/test_ROSMsg2CSVLine.py
test/test_ROSbag2CSV.py
cnspy_rosbag2csv-0.2.6.dist-info/LICENCE
cnspy_rosbag2csv-0.2.6.dist-info/METADATA
cnspy_rosbag2csv-0.2.6.dist-info/WHEEL
cnspy_rosbag2csv-0.2.6.dist-info/entry_points.txt
cnspy_rosbag2csv-0.2.6.dist-info/top_level.txt
cnspy_rosbag2csv-0.2.6.dist-info/RECORD
