Metadata-Version: 2.1
Name: cnspy_rosbag2csv
Version: 0.2.6
Summary: ROS1 rosbag to CSV file converter and vice versa.
Home-page: https://github.com/aau-cns/cnspy_rosbag2csv/
Author: Roland Jung
Author-email: roland.jung@aau.at
Project-URL: Bug Tracker, https://github.com/aau-cns/cnspy_rosbag2csv/issues
Classifier: Development Status :: 4 - Beta
Classifier: Intended Audience :: Developers
Classifier: Programming Language :: Python :: 3
Classifier: License :: OSI Approved :: GNU General Public License v3 (GPLv3)
Classifier: Operating System :: OS Independent
Requires-Python: >=3.6
License-File: LICENCE
Requires-Dist: numpy
Requires-Dist: tqdm
Requires-Dist: pandas
Requires-Dist: argparse
Requires-Dist: PyYAML
Requires-Dist: rospkg
Requires-Dist: spatialmath-python
Requires-Dist: pycryptodomex
Requires-Dist: pycryptodome
Requires-Dist: gnupg
Requires-Dist: lz4
Requires-Dist: cnspy-spatial-csv-formats >=0.2.2
